setup.py
Pydoist.egg-info/PKG-INFO
Pydoist.egg-info/SOURCES.txt
Pydoist.egg-info/dependency_links.txt
Pydoist.egg-info/requires.txt
Pydoist.egg-info/top_level.txt
lib/Pydoist.py
lib/__init__.py
scripts/pydoist