Metadata-Version: 1.1
Name: Pydoist
Version: 1.0
Summary: Todoist integration script utility
Home-page: https://github.com/Matael/pydoist
Author: Mathieu (matael) Gaborit
Author-email: mathieu@matael.org
License: WTFPL
Platform: UNKNOWN
Classifier: Programming Language :: Python :: 3
Classifier: Operating System :: OS Independent
